colablink/__init__.py
colablink/cli.py
colablink/client.py
colablink/runtime.py
colablink-1.0.0.dist-info/licenses/LICENSE
colablink-1.0.0.dist-info/METADATA
colablink-1.0.0.dist-info/WHEEL
colablink-1.0.0.dist-info/entry_points.txt
colablink-1.0.0.dist-info/top_level.txt
colablink-1.0.0.dist-info/RECORD
